pyscm/__init__.py
pyscm/_scm_utility.cpython-310-darwin.so
pyscm/model.py
pyscm/rules.py
pyscm/scm.py
pyscm/utils.py
pyscm/tests/__init__.py
pyscm/tests/test_sklearn_compatibility.py
pyscm/tests/test_utility.py
pyscm_ml-1.1.2.dist-info/LICENSE.md
pyscm_ml-1.1.2.dist-info/METADATA
pyscm_ml-1.1.2.dist-info/WHEEL
pyscm_ml-1.1.2.dist-info/top_level.txt
pyscm_ml-1.1.2.dist-info/RECORD
