Metadata-Version: 2.1
Name: pyscm-ml
Version: 1.1.2
Summary: The Set Covering Machine algorithm
Home-page: https://github.com/aldro61/pyscm
Author: Alexandre Drouin
Author-email: aldro61@gmail.com
Maintainer: Alexandre Drouin
Maintainer-email: aldro61@gmail.com
License: GPL-3
Keywords: machine-learning classification set-covering-machine rule-based-models
Classifier: Development Status :: 5 - Production/Stable
Classifier: Programming Language :: Python
Classifier: License :: OSI Approved :: GNU General Public License v3 (GPLv3)
Classifier: Operating System :: OS Independent
Classifier: Intended Audience :: Science/Research
Classifier: Topic :: Scientific/Engineering :: Artificial Intelligence
License-File: LICENSE.md
Requires-Dist: numpy<2
Requires-Dist: scikit-learn
Requires-Dist: six
